Ligare/identity/__init__.py
Ligare/identity/config.py
Ligare/identity/dependency_injection.py
Ligare/identity/SAML2/__init__.py
typings/saml2/__init__.pyi
typings/saml2/algsupport.pyi
typings/saml2/argtree.pyi
typings/saml2/assertion.pyi
typings/saml2/attribute_converter.pyi
typings/saml2/attribute_resolver.pyi
typings/saml2/authn.pyi
typings/saml2/cache.pyi
typings/saml2/cert.pyi
typings/saml2/client.pyi
typings/saml2/client_base.pyi
typings/saml2/config.pyi
typings/saml2/country_codes.pyi
typings/saml2/discovery.pyi
typings/saml2/ecp.pyi
typings/saml2/ecp_client.pyi
typings/saml2/entity.pyi
typings/saml2/eptid.pyi
typings/saml2/filter.pyi
typings/saml2/httpbase.pyi
typings/saml2/httputil.pyi
typings/saml2/ident.pyi
typings/saml2/mcache.pyi
typings/saml2/md.pyi
typings/saml2/mdbcache.pyi
typings/saml2/mdie.pyi
typings/saml2/mdstore.pyi
typings/saml2/metadata.pyi
typings/saml2/mongo_store.pyi
typings/saml2/pack.pyi
typings/saml2/population.pyi
typings/saml2/request.pyi
typings/saml2/response.pyi
typings/saml2/s_utils.pyi
typings/saml2/saml.pyi
typings/saml2/samlp.pyi
typings/saml2/sdb.pyi
typings/saml2/server.pyi
typings/saml2/sigver.pyi
typings/saml2/soap.pyi
typings/saml2/time_util.pyi
typings/saml2/validate.pyi
typings/saml2/version.pyi
typings/saml2/virtual_org.pyi
typings/saml2/attributemaps/__init__.pyi
typings/saml2/authn_context/__init__.pyi
typings/saml2/authn_context/ippword.pyi
typings/saml2/authn_context/mobiletwofactor.pyi
typings/saml2/authn_context/ppt.pyi
typings/saml2/authn_context/pword.pyi
typings/saml2/authn_context/sslcert.pyi
typings/saml2/cryptography/__init__.pyi
typings/saml2/cryptography/asymmetric.pyi
typings/saml2/cryptography/errors.pyi
typings/saml2/cryptography/pki.pyi
typings/saml2/cryptography/symmetric.pyi
typings/saml2/data/__init__.pyi
typings/saml2/data/schemas/__init__.pyi
typings/saml2/data/templates/__init__.pyi
typings/saml2/entity_category/__init__.pyi
typings/saml2/extension/__init__.pyi
Ligare.identity-0.3.0.dist-info/LICENSE.md
Ligare.identity-0.3.0.dist-info/METADATA
Ligare.identity-0.3.0.dist-info/WHEEL
Ligare.identity-0.3.0.dist-info/top_level.txt
Ligare.identity-0.3.0.dist-info/RECORD
